cbiohub/.secrets.toml
cbiohub/__init__.py
cbiohub/analyze.py
cbiohub/cli.py
cbiohub/data_commands.py
cbiohub/repomanager.py
cbiohub/study.py
cbiohub/variant.py
cbiohub-0.1.0.dist-info/LICENSE
cbiohub-0.1.0.dist-info/METADATA
cbiohub-0.1.0.dist-info/WHEEL
cbiohub-0.1.0.dist-info/entry_points.txt
cbiohub-0.1.0.dist-info/RECORD
