Metadata-Version: 2.1
Name: cbiohub
Version: 0.1.0
Summary: Convenience functions for accessing cBioPortal data files
Author: Ino de Bruijn
Author-email: ino@ino.bio
Requires-Python: >=3.12
Classifier: Programming Language :: Python :: 3
Classifier: Programming Language :: Python :: 3.12
Requires-Dist: click (>=8.1.7,<9.0.0)
Requires-Dist: duckdb (>=1.0.0,<2.0.0)
Requires-Dist: dynaconf (>=3.2.6,<4.0.0)
Requires-Dist: pandas (>=2.2.2,<3.0.0)
Requires-Dist: pyarrow (>=17.0.0,<18.0.0)
Requires-Dist: tabulate (>=0.9.0,<0.10.0)
Requires-Dist: tqdm (>=4.66.5,<5.0.0)
